ermeopy/__init__.py
ermeopy/const.py
ermeopy/ermeo.py
ermeopy/resource.py
ermeopy/tools.py
ermeopy/common/__init__.py
ermeopy/common/auth.py
ermeopy/common/folder.py
ermeopy/common/user.py
ermeopy/common/widget.py
ermeopy/schema/__init__.py
ermeopy/schema/common_schema.py
ermeopy/schema/folder_schema.py
ermeopy/schema/user_schema.py
ermeopy/schema/widget_schema.py
tests/__init__.py
tests/conf.py
tests/test_ermeo.py
sdk_ermeo-1.18.5.dist-info/LICENSE
sdk_ermeo-1.18.5.dist-info/METADATA
sdk_ermeo-1.18.5.dist-info/WHEEL
sdk_ermeo-1.18.5.dist-info/top_level.txt
sdk_ermeo-1.18.5.dist-info/RECORD
